xcube/__init__.py
xcube/_modidx.py
xcube/basics.py
xcube/collab.py
xcube/fastai_imports.py
xcube/imports.py
xcube/layers.py
xcube/metrics.py
xcube/torch_imports.py
xcube/utils.py
xcube/data/__init__.py
xcube/data/all.py
xcube/data/external.py
xcube/data/transforms.py
xcube/l2r/__init__.py
xcube/l2r/all.py
xcube/l2r/callbacks.py
xcube/l2r/gradients.py
xcube/l2r/learner.py
xcube/l2r/data/__init__.py
xcube/l2r/data/all.py
xcube/l2r/data/boot.py
xcube/l2r/data/info_gain.py
xcube/l2r/data/load.py
xcube/l2r/data/stat.py
xcube/l2r/models/__init__.py
xcube/l2r/models/all.py
xcube/l2r/models/core.py
xcube/text/__init__.py
xcube/text/all.py
xcube/text/callbacks.py
xcube/text/learner.py
xcube/text/models/__init__.py
xcube/text/models/all.py
xcube/text/models/core.py
xcube-0.0.9.dist-info/LICENSE
xcube-0.0.9.dist-info/METADATA
xcube-0.0.9.dist-info/WHEEL
xcube-0.0.9.dist-info/entry_points.txt
xcube-0.0.9.dist-info/top_level.txt
xcube-0.0.9.dist-info/RECORD
