Metadata-Version: 2.1
Name: xcube
Version: 0.0.9
Summary: Extreme Multi-Label Text Classification
Home-page: https://github.com/debjyotiSRoy/xcube
Author: debjyotiSRoy
Author-email: debjyoti.saharoy@gmail.com
License: Apache Software License 2.0
Keywords: nbdev jupyter notebook python
Classifier: Development Status :: 4 - Beta
Classifier: Intended Audience :: Developers
Classifier: Natural Language :: English
Classifier: Programming Language :: Python :: 3.9
Classifier: Programming Language :: Python :: 3.10
Classifier: License :: OSI Approved :: Apache Software License
Requires-Python: >=3.9
License-File: LICENSE
Requires-Dist: fastai (>=2.7.12)
Requires-Dist: fastcore (>=1.5.29)
Requires-Dist: fastdownload (>=0.0.7)
Requires-Dist: fastprogress (>=1.0.3)
Requires-Dist: pandas (>=2.0.1)
Requires-Dist: scikit-learn
Requires-Dist: seaborn (>=0.12.2)
Requires-Dist: icecream (>=2.1.3)
Requires-Dist: matplotlib
Requires-Dist: requests
Requires-Dist: pyyaml
Requires-Dist: pillow (>=9.4.0)
Requires-Dist: scikit-learn (>=1.2.0)
Requires-Dist: scipy (>=1.10.1)
Requires-Dist: spacy (<4,>=3.5.2)
Requires-Dist: packaging
Requires-Dist: accelerate (>=0.21.0)
Requires-Dist: wandb (>=0.15.9)
Requires-Dist: ipython (>=8.12.0)
Requires-Dist: bs4
Requires-Dist: torch (>=2.0.0)
Provides-Extra: dev
